{"meta":{"instanceId":"c8c9ba5d3eb26ae47a06d24ff164a01c0d73ed4753a74903c2bb609d434a0f6b"},"nodes":[{"id":"4a3b7b39-71a7-4a59-8c91-0ebf9fef29b2","name":"Workflow description","type":"n8n-nodes-base.stickyNote","position":[-250,-250],"parameters":{"color":5,"width":272,"height":912,"content":"## Workflow overview\n\nSimple recipe finder app. User enters an ingredient or dish into a form. Workflow calls API Ninjas Recipe API and shows the recipe result back on the form page.\n\n### Setup\n- **Form Trigger - Recipe Finder**: the entry form with a `query` field.\n- **Fetch Recipe from API Ninjas**: API call node using header auth.\n- **Show Recipe Result**: returns title, ingredients, instructions in formatted text.\n\n### Flow\n1. Form trigger waits for input.\n2. Passes query to API Ninjas.\n3. Fetches recipe.\n4. Shows formatted recipe back to user.\n\n### Notes\nQuick demo of how to build a recipe finder workflow in n8n. Expand easily with more features like multiple recipes, emails, or saving results."},"typeVersion":1},{"id":"891b66aa-1620-4867-b27c-b978588a5462","name":"Fetch Recipe from API Ninjas","type":"n8n-nodes-base.httpRequest","position":[208,0],"parameters":{"url":"https://api.api-ninjas.com/v1/recipe","options":{},"sendQuery":true,"authentication":"genericCredentialType","genericAuthType":"httpHeaderAuth","queryParameters":{"parameters":[{"name":"query","value":"={{ $json.query }}"}]}},"credentials":{"httpHeaderAuth":{"id":"IU0D73p4jW1pvQE8","name":"API Ninjas Credential"}},"typeVersion":4.2},{"id":"51dbc266-c345-4334-9349-f66a45ff5350","name":"Form Trigger - Recipe Finder","type":"n8n-nodes-base.formTrigger","position":[0,0],"webhookId":"7361e34a-fc0e-4125-8b89-6c5774c86b0b","parameters":{"options":{},"formTitle":"Find a recipe","formFields":{"values":[{"fieldLabel":"query"}]},"responseMode":"lastNode"},"typeVersion":2.2},{"id":"2bbcb8e8-b63f-45a8-b141-07300ef724ba","name":"Show Recipe Result","type":"n8n-nodes-base.form","position":[448,0],"webhookId":"51c635a1-9803-4fc0-a3b2-a7058cbd7356","parameters":{"options":{},"operation":"completion","completionTitle":"={{ $json.title }}","completionMessage":"=<h3>Ingredients</h3>\n{{ $json.ingredients }}\n\n\n<h3>Instructions</h3>\n{{ $json.instructions }}"},"typeVersion":1}],"pinData":{},"connections":{"Fetch Recipe from API Ninjas":{"main":[[{"node":"Show Recipe Result","type":"main","index":0}]]},"Form Trigger - Recipe Finder":{"main":[[{"node":"Fetch Recipe from API Ninjas","type":"main","index":0}]]}}}